ptmodels/Classifier.py
ptmodels-0.1.3.dist-info/LICENSE.txt
ptmodels-0.1.3.dist-info/METADATA
ptmodels-0.1.3.dist-info/WHEEL
ptmodels-0.1.3.dist-info/top_level.txt
ptmodels-0.1.3.dist-info/RECORD
