Metadata-Version: 2.1
Name: ptmodels
Version: 0.1.3
Summary: A image classifier using pre-trained models
Home-page: https://github.com/rafsunsheikh/ptmodels
Download-URL: https://github.com/rafsunsheikh/ptmodels/archive/refs/tags/0.1.2.tar.gz
Author: MD Rafsun sheikh
Author-email: rafsunsheikh <rafsun.sheikh@gmail.com>
License: MIT
Project-URL: Homepage, https://github.com/rafsunsheikh/ptmodels
Project-URL: Bug Tracker, https://github.com/rafsunsheikh/ptmodels/issues
Keywords: Image,Classification,Pre-trained Model
Classifier: Programming Language :: Python :: 3
Classifier: License :: OSI Approved :: MIT License
Classifier: Operating System :: OS Independent
Requires-Python: >=3.7
License-File: LICENSE.txt
Requires-Dist: numpy
Requires-Dist: pandas
Requires-Dist: tensorflow
Requires-Dist: sklearn
Requires-Dist: keras
